CHANGES.txt
LICENSE.txt
MANIFEST.in
README.txt
setup.py
js/__init__.py
js.jquery_metadata.egg-info/PKG-INFO
js.jquery_metadata.egg-info/SOURCES.txt
js.jquery_metadata.egg-info/dependency_links.txt
js.jquery_metadata.egg-info/entry_points.txt
js.jquery_metadata.egg-info/namespace_packages.txt
js.jquery_metadata.egg-info/not-zip-safe
js.jquery_metadata.egg-info/requires.txt
js.jquery_metadata.egg-info/top_level.txt
js/jquery_metadata/__init__.py
js/jquery_metadata/test_jquery_metadata.txt
js/jquery_metadata/resources/jquery.metadata.js