Metadata-Version: 1.0
Name: js.jquery-metadata
Version: 2.1
Summary: Fanstatic packaging of jQuery Metadata
Home-page: UNKNOWN
Author: Fanstatic Developers
Author-email: fanstatic@googlegroups.com
License: BSD
Platform: UNKNOWN
